abstractmemory/__init__.py
abstractmemory/simple.py
abstractmemory/cognitive/__init__.py
abstractmemory/components/__init__.py
abstractmemory/components/core.py
abstractmemory/components/episodic.py
abstractmemory/components/semantic.py
abstractmemory/components/working.py
abstractmemory/core/__init__.py
abstractmemory/core/interfaces.py
abstractmemory/core/temporal.py
abstractmemory/embeddings/__init__.py
abstractmemory/embeddings/sentence_transformer_provider.py
abstractmemory/graph/__init__.py
abstractmemory/graph/knowledge_graph.py
abstractmemory/storage/__init__.py
abstractmemory/storage/dual_manager.py
abstractmemory/storage/lancedb_storage.py
abstractmemory/storage/markdown_storage.py
abstractmemory-0.2.3.dist-info/licenses/LICENSE
abstractmemory-0.2.3.dist-info/METADATA
abstractmemory-0.2.3.dist-info/WHEEL
abstractmemory-0.2.3.dist-info/top_level.txt
abstractmemory-0.2.3.dist-info/RECORD
