Metadata-Version: 2.4
Name: AbstractMemory
Version: 0.2.3
Summary: Production-ready memory system for LLM agents - NO MOCKS, real semantic search, clear LLM vs embedding provider separation
Author-email: Laurent-Philippe Albou <lpalbou@gmail.com>
Maintainer-email: Laurent-Philippe Albou <lpalbou@gmail.com>
License-Expression: MIT
Project-URL: Homepage, https://github.com/lpalbou/AbstractMemory
Project-URL: Documentation, https://github.com/lpalbou/AbstractMemory#readme
Project-URL: Repository, https://github.com/lpalbou/AbstractMemory
Project-URL: Bug Reports, https://github.com/lpalbou/AbstractMemory/issues
Keywords: llm,memory,semantic-search,embeddings,ai,agents,knowledge-graph,temporal,grounded-memory,vector-search
Classifier: Development Status :: 5 - Production/Stable
Classifier: Intended Audience :: Developers
Classifier: Programming Language :: Python :: 3
Classifier: Programming Language :: Python :: 3.8
Classifier: Programming Language :: Python :: 3.9
Classifier: Programming Language :: Python :: 3.10
Classifier: Programming Language :: Python :: 3.11
Classifier: Programming Language :: Python :: 3.12
Classifier: Topic :: Scientific/Engineering :: Artificial Intelligence
Classifier: Topic :: Software Development :: Libraries :: Python Modules
Classifier: Topic :: Software Development :: Libraries :: Application Frameworks
Requires-Python: >=3.8
License-File: LICENSE
Requires-Dist: networkx>=3.0
Provides-Extra: dev
Requires-Dist: pytest; extra == "dev"
Requires-Dist: black; extra == "dev"
Requires-Dist: mypy; extra == "dev"
Provides-Extra: llm
Requires-Dist: abstractcore>=2.1.0; extra == "llm"
Provides-Extra: embeddings
Requires-Dist: abstractcore>=2.1.0; extra == "embeddings"
Requires-Dist: lancedb>=0.6.0; extra == "embeddings"
Requires-Dist: sentence-transformers>=2.0.0; extra == "embeddings"
Provides-Extra: storage
Requires-Dist: lancedb>=0.6.0; extra == "storage"
Provides-Extra: all
Requires-Dist: abstractcore>=2.1.0; extra == "all"
Requires-Dist: lancedb>=0.6.0; extra == "all"
Requires-Dist: sentence-transformers>=2.0.0; extra == "all"
Dynamic: license-file
